roner/__init__.py
roner/model.py
roner-1.0.3.dist-info/LICENSE
roner-1.0.3.dist-info/METADATA
roner-1.0.3.dist-info/WHEEL
roner-1.0.3.dist-info/top_level.txt
roner-1.0.3.dist-info/RECORD
